mcp_server_maven/__init__.py
mcp_server_maven/__main__.py
mcp_server_maven/server.py
mcp_server_maven/utils.py
mcp_server_maven/tests/__init__.py
mcp_server_maven/tests/test_server.py
mcp_server_maven-0.1.2.dist-info/METADATA
mcp_server_maven-0.1.2.dist-info/WHEEL
mcp_server_maven-0.1.2.dist-info/entry_points.txt
mcp_server_maven-0.1.2.dist-info/licenses/LICENSE
mcp_server_maven-0.1.2.dist-info/RECORD
