Metadata-Version: 2.4
Name: mcp-server-maven
Version: 0.1.2
Summary: Add your description here
License-File: LICENSE
Requires-Python: >=3.10
Requires-Dist: httpx<0.28
Requires-Dist: mcp>=1.1.3
Requires-Dist: pydantic>=2.0.0
Requires-Dist: readabilipy>=0.2.0
Requires-Dist: requests>=2.32.3
